estudo_pkg/__init__.py
estudo_pkg/myLib.py
estudo_pkg-0.1.1.dist-info/entry_points.txt
estudo_pkg-0.1.1.dist-info/WHEEL
estudo_pkg-0.1.1.dist-info/METADATA
estudo_pkg-0.1.1.dist-info/RECORD
