Metadata-Version: 2.1
Name: estudo-pkg
Version: 0.1.1
Summary: 
Author: pabloverly
Author-email: pablopierre.pv@gmail.com
Requires-Python: >=3.7,<4.0
Classifier: Programming Language :: Python :: 3
Classifier: Programming Language :: Python :: 3.10
Classifier: Programming Language :: Python :: 3.7
Classifier: Programming Language :: Python :: 3.8
Classifier: Programming Language :: Python :: 3.9
Requires-Dist: httpx (>=0.20.0,<0.21.0)
